<?xml version="1.0" encoding="utf-8"?>
<!DOCTYPE hibernate-mapping PUBLIC "-//Hibernate/Hibernate Mapping DTD 3.0//EN"
"http://www.hibernate.org/dtd/hibernate-mapping-3.0.dtd">
<!-- 
    Mapping file autogenerated by MyEclipse Persistence Tools
-->
<hibernate-mapping>
    <class name="com.domain.Pictures" table="pictures" catalog="weibo">
        <id name="picturesId" type="java.lang.Integer">
            <column name="pictures_id" />
            <generator class="native" />
        </id>
        <many-to-one name="messages" class="com.domain.Messages" fetch="select">
            <column name="messages_id" />
        </many-to-one>
        <many-to-one name="users" class="com.domain.Users" fetch="select">
            <column name="users_id" />
        </many-to-one>
        <property name="picturesUrl" type="java.lang.String">
            <column name="pictures_url" length="200" />
        </property>
        <property name="picturesType" type="java.lang.String">
            <column name="pictures_type" length="20" />
        </property>
        <property name="picturesTime" type="java.sql.Timestamp">
            <column name="pictures_time" length="19" />
        </property>
    </class>
</hibernate-mapping>
